LICENSE.txt
MANIFEST.in
README.md
requirements.txt
setup.py
nlup/__init__.py
nlup/confusion.py
nlup/decorators.py
nlup/jsonable.py
nlup/perceptron.py
nlup/pklable.py
nlup/readers.py
nlup/timer.py
nlup/util.py
nlup.egg-info/PKG-INFO
nlup.egg-info/SOURCES.txt
nlup.egg-info/dependency_links.txt
nlup.egg-info/requires.txt
nlup.egg-info/top_level.txt