Metadata-Version: 2.1
Name: nlup
Version: 0.7.post1
Summary: Core libraries for natural language processing
Home-page: http://github.com/cslu-nlp/nlup/
Author: Kyle Gorman
Author-email: kylebgorman@gmail.com
License: MIT
Keywords: nlp,natural language processing,text,text processing,ai,artificial intelligence,neural net,perceptron,data,science,statistics,data science,math,machine learning,computer science,information theory
Platform: UNKNOWN
Classifier: Programming Language :: Python
Classifier: Programming Language :: Python :: 3.5
Classifier: Programming Language :: Python :: 3.6
Classifier: Development Status :: 5 - Production/Stable
Classifier: Environment :: Other Environment
Classifier: Environment :: Console
Classifier: Intended Audience :: Developers
Classifier: License :: OSI Approved :: MIT License
Classifier: Operating System :: OS Independent
Classifier: Topic :: Software Development :: Libraries :: Python Modules
Classifier: Topic :: Text Processing :: Linguistic
Classifier: Topic :: Text Processing :: Filters
Classifier: Topic :: Text Processing :: General
Classifier: Topic :: Text Processing :: Indexing
Classifier: Topic :: Scientific/Engineering :: Mathematics
Classifier: Topic :: Scientific/Engineering :: Artificial Intelligence
